
{
  "level": "N4",
  "questions": [
    {
      "id": 1,
      "question": "彼は毎日＿＿＿日本語を勉強しています。",
      "options": ["を", "で", "に", "と"],
      "correct": 0,
      "explanation": "「を」は動作の対象を示す助詞です。"
    },
    {
      "id": 2,
      "question": "昨日、友達＿＿＿映画を見ました。",
      "options": ["と", "を", "に", "で"],
      "correct": 0,
      "explanation": "「と」は一緒に行動する相手を表す助詞です。"
    },
    {
      "id": 3,
      "question": "図書館＿＿＿本を借りました。",
      "options": ["を", "で", "に", "と"],
      "correct": 1,
      "explanation": "「で」は動作が行われる場所を示す助詞です。"
    },
    {
      "id": 4,
      "question": "来年、大学＿＿＿入ります。",
      "options": ["を", "で", "に", "と"],
      "correct": 2,
      "explanation": "「に」は目的地や時間を示す助詞です。"
    },
    {
      "id": 5,
      "question": "この本はとても＿＿＿です。",
      "options": ["おもしろい", "おもしろく", "おもしろかった", "おもしろくて"],
      "correct": 0,
      "explanation": "現在の状態を表すので「おもしろい」が正解です。"
    },
    {
      "id": 6,
      "question": "雨が降って＿＿＿、出かけませんでした。",
      "options": ["ので", "けれど", "から", "でも"],
      "correct": 0,
      "explanation": "「ので」は理由を表す接続助詞です。"
    },
    {
      "id": 7,
      "question": "日本語は難しい＿＿＿、楽しいです。",
      "options": ["ので", "けれど", "から", "でも"],
      "correct": 1,
      "explanation": "「けれど」は逆接の意味を表します。"
    },
    {
      "id": 8,
      "question": "明日の会議＿＿＿参加します。",
      "options": ["を", "で", "に", "と"],
      "correct": 2,
      "explanation": "「に」は参加する対象を示します。"
    },
    {
      "id": 9,
      "question": "この料理は＿＿＿作りましたか。",
      "options": ["だれ", "だれが", "だれを", "だれに"],
      "correct": 1,
      "explanation": "「だれが」は動作の主体を聞く疑問詞です。"
    },
    {
      "id": 10,
      "question": "今度の休み＿＿＿、どこに行きますか。",
      "options": ["を", "で", "に", "と"],
      "correct": 2,
      "explanation": "「に」は時間を表す助詞です。"
    }
  ]
}
